UniCover-0.1.dist-info/DESCRIPTION.rst
UniCover-0.1.dist-info/METADATA
UniCover-0.1.dist-info/RECORD
UniCover-0.1.dist-info/WHEEL
UniCover-0.1.dist-info/entry_points.txt
UniCover-0.1.dist-info/metadata.json
UniCover-0.1.dist-info/top_level.txt
unicover/__init__.py
unicover/blocks.py
unicover/ranges.py
unicover/unicover.py
