Metadata-Version: 2.0
Name: UniCover
Version: 0.1
Summary: Displays Unicode chars coverage of system fonts
Home-page: https://github.com/drastus/unicover
Author: Michał Górny
Author-email: zrchos@gmail.com
License: MIT
Platform: UNKNOWN
Classifier: Development Status :: 5 - Production/Stable
Classifier: Environment :: Console
Classifier: License :: OSI Approved :: MIT License
Classifier: Natural Language :: English
Classifier: Programming Language :: Python :: 3
Classifier: Topic :: System :: Console Fonts
Classifier: Topic :: Text Processing :: Fonts
Classifier: Topic :: Utilities
Requires-Dist: Python-fontconfig
Requires-Dist: freetype-py
